competition/README.md
competition/IJCAI_2024_CAR/train_paddle.py
competition/IJCAI_2024_CAR/untitled.py
competition/IJCAI_2024_CAR/model/src/__init__.py
competition/IJCAI_2024_CAR/model/src/data/__init__.py
competition/IJCAI_2024_CAR/model/src/data/base_datamodule.py
competition/IJCAI_2024_CAR/model/src/data/cfd_datamodule.py
competition/IJCAI_2024_CAR/model/src/networks/ConvUNet2.py
competition/IJCAI_2024_CAR/model/src/networks/__init__.py
competition/IJCAI_2024_CAR/model/src/networks/base_model.py
competition/IJCAI_2024_CAR/model/src/networks/net_utils.py
competition/IJCAI_2024_CAR/model/src/networks/utils/dot_dict.py
competition/IJCAI_2024_CAR/model/src/networks/utils/paddle_aux.py
competition/IJCAI_2024_CAR/model/src/utils/average_meter.py
competition/IJCAI_2024_CAR/model/src/utils/dot_dict.py
deploy/__init__.py
deploy/python_infer/__init__.py
deploy/python_infer/base.py
deploy/python_infer/pinn_predictor.py
docker/Dockerfile
docker/run.sh
jaxpi/setup.py
jaxpi/examples/adv/eval.py
jaxpi/examples/adv/main.py
jaxpi/examples/adv/models.py
jaxpi/examples/adv/sweep.py
jaxpi/examples/adv/train.py
jaxpi/examples/adv/utils.py
jaxpi/examples/adv/configs/default.py
jaxpi/examples/adv/configs/default_ntk.py
jaxpi/examples/adv/configs/no_causal.py
jaxpi/examples/adv/configs/no_fourier_feature.py
jaxpi/examples/adv/configs/no_grad_norm.py
jaxpi/examples/adv/configs/no_rwf.py
jaxpi/examples/adv/configs/no_time_period.py
jaxpi/examples/adv/configs/only_fourier_feature.py
jaxpi/examples/adv/configs/plain.py
jaxpi/examples/adv/configs/sota.py
jaxpi/examples/adv/configs/sweep.py
jaxpi/examples/allen_cahn/eval.py
jaxpi/examples/allen_cahn/main.py
jaxpi/examples/allen_cahn/models.py
jaxpi/examples/allen_cahn/sweep.py
jaxpi/examples/allen_cahn/train.py
jaxpi/examples/allen_cahn/utils.py
jaxpi/examples/allen_cahn/configs/default.py
jaxpi/examples/allen_cahn/configs/default_ntk.py
jaxpi/examples/allen_cahn/configs/no_causal.py
jaxpi/examples/allen_cahn/configs/no_fourier_feature.py
paddlesci-1.4.0.dist-info/licenses/LICENSE
paddlesci-1.4.0.dist-info/METADATA
paddlesci-1.4.0.dist-info/WHEEL
paddlesci-1.4.0.dist-info/top_level.txt
paddlesci-1.4.0.dist-info/RECORD
