Metadata-Version: 2.4
Name: paddlesci
Version: 1.4.0
Summary: A library for scientific machine learning
Home-page: https://github.com/PaddlePaddle/PaddleScience
Author: PaddlePaddle
License: Apache-2.0
Project-URL: Homepage, https://github.com/PaddlePaddle/PaddleScience
Project-URL: Bug Tracker, https://github.com/PaddlePaddle/PaddleScience/issues
Project-URL: Changelog, https://github.com/PaddlePaddle/PaddleScience/releases
Project-URL: Documentation, https://paddlescience-docs.readthedocs.io/zh/latest/
Keywords: Machine learning,Deep learning,Differential equations,AI4Science,Physics-informed neural networks,PaddlePaddle
Classifier: Development Status :: 5 - Production/Stable
Classifier: Intended Audience :: Science/Research
Classifier: License :: OSI Approved :: Apache Software License
Classifier: Programming Language :: Python :: 3 :: Only
Classifier: Programming Language :: Python :: 3.8
Classifier: Programming Language :: Python :: 3.9
Classifier: Programming Language :: Python :: 3.10
Classifier: Topic :: Scientific/Engineering
Classifier: Topic :: Scientific/Engineering :: Artificial Intelligence
Classifier: Topic :: Scientific/Engineering :: Mathematics
Requires-Python: >=3.8
License-File: LICENSE
Requires-Dist: colorlog
Requires-Dist: einops
Requires-Dist: h5py
Requires-Dist: hydra-core
Requires-Dist: imageio
Requires-Dist: matplotlib
Requires-Dist: meshio==5.3.4
Requires-Dist: numpy<2.0.0,>=1.20.0
Requires-Dist: pydantic>=2.5.0
Requires-Dist: pyevtk
Requires-Dist: pyyaml
Requires-Dist: requests
Requires-Dist: scikit-learn<1.5.0
Requires-Dist: scikit-optimize
Requires-Dist: scipy
Requires-Dist: seaborn
Requires-Dist: sympy
Requires-Dist: tqdm
Requires-Dist: typing-extensions
Requires-Dist: wget
Dynamic: home-page
Dynamic: license-file
